assets/logo-32x32.png
assets/logo-64x64.png
psysh_kernel/__init__.py
psysh_kernel/__main__.py
psysh_kernel/kernel.json
psysh_kernel/kernel.py
psysh_kernel-0.1.4.data/data/share/jupyter/kernels/octave/kernel.json
psysh_kernel-0.1.4.data/data/share/jupyter/kernels/octave/logo-32x32.png
psysh_kernel-0.1.4.data/data/share/jupyter/kernels/octave/logo-64x64.png
psysh_kernel-0.1.4.dist-info/LICENSE.txt
psysh_kernel-0.1.4.dist-info/METADATA
psysh_kernel-0.1.4.dist-info/WHEEL
psysh_kernel-0.1.4.dist-info/top_level.txt
psysh_kernel-0.1.4.dist-info/RECORD
