Metadata-Version: 2.1
Name: psysh-kernel
Version: 0.1.4
Summary: A PHP kernel for Jupyter/IPython, based on MetaKernel
Home-page: https://github.com/jaesin/psysh_kernel
Author: Jaesin Mulenex
Author-email: Jaesin@users.noreply.github.com
Maintainer: Jaesin Mulenex
License: BSD
Platform: UNKNOWN
Classifier: Intended Audience :: Developers
Classifier: License :: OSI Approved :: BSD License
Classifier: Operating System :: OS Independent
Classifier: Programming Language :: Python
Classifier: Programming Language :: Python :: 2.7
Classifier: Programming Language :: Python :: 3.7
Classifier: Topic :: Scientific/Engineering
Classifier: Topic :: Software Development
Classifier: Topic :: System :: System Shells
Requires: metakernel (>=0.20.11)
Requires: jupyter_client (>=4.3.0)
Requires: ipykernel
Requires-Dist: metakernel (>=0.20.11)
Requires-Dist: jupyter-client (>=4.3.0)
Requires-Dist: ipykernel
